{
  "1": "https://www.arabic-toons.com/batman-s1-1433591670-11765.html#sets",
  "2": "https://www.arabic-toons.com/batman-s1-1433591670-11766.html#sets",
  "3": "https://www.arabic-toons.com/batman-s1-1433591670-11767.html#sets",
  "4": "https://www.arabic-toons.com/batman-s1-1433591670-11768.html#sets",
  "5": "https://www.arabic-toons.com/batman-s1-1433591670-11769.html#sets",
  "6": "https://www.arabic-toons.com/batman-s1-1433591670-11770.html#sets",
  "7": "https://www.arabic-toons.com/batman-s1-1433591670-11771.html#sets",
  "8": "https://www.arabic-toons.com/batman-s1-1433591670-11772.html#sets",
  "9": "https://www.arabic-toons.com/batman-s1-1433591670-11773.html#sets",
  "10": "https://www.arabic-toons.com/batman-s1-1433591670-11774.html#sets",
  "11": "https://www.arabic-toons.com/batman-s1-1433591670-11775.html#sets",
  "12": "https://www.arabic-toons.com/batman-s1-1433591670-11776.html#sets",
  "13": "https://www.arabic-toons.com/batman-s1-1433591670-11777.html#sets",
  "14": "https://www.arabic-toons.com/batman-s1-1433591670-11778.html#sets",
  "15": "https://www.arabic-toons.com/batman-s1-1433591670-11779.html#sets",
  "16": "https://www.arabic-toons.com/batman-s1-1433591670-11780.html#sets",
  "17": "https://www.arabic-toons.com/batman-s1-1433591670-11781.html#sets",
  "18": "https://www.arabic-toons.com/batman-s1-1433591670-11782.html#sets",
  "19": "https://www.arabic-toons.com/batman-s1-1433591670-11783.html#sets",
  "20": "https://www.arabic-toons.com/batman-s1-1433591670-11784.html#sets",
  "21": "https://www.arabic-toons.com/batman-s1-1433591670-11785.html#sets",
  "22": "https://www.arabic-toons.com/batman-s1-1433591670-11786.html#sets",
  "23": "https://www.arabic-toons.com/batman-s1-1433591670-11787.html#sets",
  "24": "https://www.arabic-toons.com/batman-s1-1433591670-11788.html#sets",
  "25": "https://www.arabic-toons.com/batman-s1-1433591670-11789.html#sets",
  "26": "https://www.arabic-toons.com/batman-s1-1433591670-11790.html#sets",
  "27": "https://www.arabic-toons.com/batman-s1-1433591670-11791.html#sets"
}