{
  "1": "https://www.arabic-toons.com/driland-1437356611-9503.html#sets",
  "2": "https://www.arabic-toons.com/driland-1437356611-9504.html#sets",
  "3": "https://www.arabic-toons.com/driland-1437356611-9505.html#sets",
  "4": "https://www.arabic-toons.com/driland-1437356611-9506.html#sets",
  "5": "https://www.arabic-toons.com/driland-1437356611-9507.html#sets",
  "6": "https://www.arabic-toons.com/driland-1437356611-9508.html#sets",
  "7": "https://www.arabic-toons.com/driland-1437356611-9509.html#sets",
  "8": "https://www.arabic-toons.com/driland-1437356611-9510.html#sets",
  "9": "https://www.arabic-toons.com/driland-1437356611-9511.html#sets",
  "10": "https://www.arabic-toons.com/driland-1437356611-9512.html#sets",
  "11": "https://www.arabic-toons.com/driland-1437356611-9513.html#sets",
  "12": "https://www.arabic-toons.com/driland-1437356611-9514.html#sets",
  "13": "https://www.arabic-toons.com/driland-1437356611-9515.html#sets",
  "14": "https://www.arabic-toons.com/driland-1437356611-9516.html#sets",
  "15": "https://www.arabic-toons.com/driland-1437356611-9517.html#sets",
  "16": "https://www.arabic-toons.com/driland-1437356611-9518.html#sets",
  "17": "https://www.arabic-toons.com/driland-1437356611-9519.html#sets",
  "18": "https://www.arabic-toons.com/driland-1437356611-9520.html#sets",
  "19": "https://www.arabic-toons.com/driland-1437356611-9521.html#sets",
  "20": "https://www.arabic-toons.com/driland-1437356611-9522.html#sets",
  "21": "https://www.arabic-toons.com/driland-1437356611-9523.html#sets",
  "22": "https://www.arabic-toons.com/driland-1437356611-9524.html#sets",
  "23": "https://www.arabic-toons.com/driland-1437356611-9525.html#sets",
  "24": "https://www.arabic-toons.com/driland-1437356611-9526.html#sets",
  "25": "https://www.arabic-toons.com/driland-1437356611-9527.html#sets",
  "26": "https://www.arabic-toons.com/driland-1437356611-9528.html#sets",
  "27": "https://www.arabic-toons.com/driland-1437356611-9529.html#sets",
  "28": "https://www.arabic-toons.com/driland-1437356611-9530.html#sets",
  "29": "https://www.arabic-toons.com/driland-1437356611-9531.html#sets",
  "30": "https://www.arabic-toons.com/driland-1437356611-9532.html#sets",
  "31": "https://www.arabic-toons.com/driland-1437356611-9533.html#sets",
  "32": "https://www.arabic-toons.com/driland-1437356611-9534.html#sets",
  "33": "https://www.arabic-toons.com/driland-1437356611-45541.html#sets",
  "34": "https://www.arabic-toons.com/driland-1437356611-45542.html#sets",
  "35": "https://www.arabic-toons.com/driland-1437356611-45543.html#sets",
  "36": "https://www.arabic-toons.com/driland-1437356611-45544.html#sets",
  "37": "https://www.arabic-toons.com/driland-1437356611-45545.html#sets"
}