{
  "1": "https://www.arabic-toons.com/lbx-1432543830-12575.html#sets",
  "2": "https://www.arabic-toons.com/lbx-1432543830-12576.html#sets",
  "3": "https://www.arabic-toons.com/lbx-1432543830-12577.html#sets",
  "4": "https://www.arabic-toons.com/lbx-1432543830-12578.html#sets",
  "5": "https://www.arabic-toons.com/lbx-1432543830-12579.html#sets",
  "6": "https://www.arabic-toons.com/lbx-1432543830-12580.html#sets",
  "7": "https://www.arabic-toons.com/lbx-1432543830-12581.html#sets",
  "8": "https://www.arabic-toons.com/lbx-1432543830-12582.html#sets",
  "9": "https://www.arabic-toons.com/lbx-1432543830-12583.html#sets",
  "10": "https://www.arabic-toons.com/lbx-1432543830-12584.html#sets",
  "11": "https://www.arabic-toons.com/lbx-1432543830-12585.html#sets",
  "12": "https://www.arabic-toons.com/lbx-1432543830-12586.html#sets",
  "13": "https://www.arabic-toons.com/lbx-1432543830-12587.html#sets",
  "14": "https://www.arabic-toons.com/lbx-1432543830-12588.html#sets",
  "15": "https://www.arabic-toons.com/lbx-1432543830-12589.html#sets",
  "16": "https://www.arabic-toons.com/lbx-1432543830-12590.html#sets",
  "17": "https://www.arabic-toons.com/lbx-1432543830-12591.html#sets",
  "18": "https://www.arabic-toons.com/lbx-1432543830-12592.html#sets",
  "19": "https://www.arabic-toons.com/lbx-1432543830-12593.html#sets",
  "20": "https://www.arabic-toons.com/lbx-1432543830-12594.html#sets",
  "21": "https://www.arabic-toons.com/lbx-1432543830-12595.html#sets",
  "22": "https://www.arabic-toons.com/lbx-1432543830-12596.html#sets",
  "23": "https://www.arabic-toons.com/lbx-1432543830-12597.html#sets",
  "24": "https://www.arabic-toons.com/lbx-1432543830-12598.html#sets",
  "25": "https://www.arabic-toons.com/lbx-1432543830-12599.html#sets",
  "26": "https://www.arabic-toons.com/lbx-1432543830-45191.html#sets"
}